Metadata-Version: 2.4
Name: adafruit-circuitpython-datetime
Version: 1.4.4
Summary: Subset of CPython datetime module
Author-email: Adafruit Industries <circuitpython@adafruit.com>
License: MIT
Project-URL: Homepage, https://github.com/adafruit/Adafruit_CircuitPython_datetime
Keywords: adafruit,blinka,circuitpython,micropython,datetime,date,time,timedelta,tzinfo,timezone
Classifier: Intended Audience :: Developers
Classifier: Topic :: Software Development :: Libraries
Classifier: Topic :: Software Development :: Embedded Systems
Classifier: Topic :: System :: Hardware
Classifier: License :: OSI Approved :: MIT License
Classifier: Programming Language :: Python :: 3
License-File: LICENSE
Requires-Dist: Adafruit-Blinka
Provides-Extra: optional
Dynamic: license-file
